python_trueconf_room-1.0.0.dist-info/licenses/LICENSE
trueconf_room/__init__.py
trueconf_room/_version.py
trueconf_room/consts.py
trueconf_room/methods.py
trueconf_room/utils.py
python_trueconf_room-1.0.0.dist-info/METADATA
python_trueconf_room-1.0.0.dist-info/WHEEL
python_trueconf_room-1.0.0.dist-info/top_level.txt
python_trueconf_room-1.0.0.dist-info/RECORD
