Metadata-Version: 2.4
Name: python-trueconf-room
Version: 1.0.0
Summary: A Python library for the TrueConf Room API
Author-email: TrueConf LLC <info@trueconf.com>, Andrey Zobov <azobov@trueconf.com>
License-Expression: BSD-3-Clause-Clear
Project-URL: Homepage, https://github.com/TrueConf/python-trueconf-room
Project-URL: Repository, https://github.com/TrueConf/python-trueconf-room
Project-URL: Documentation, https://trueconf.com/docs/videosdk/en/introduction/common
Project-URL: Issues, https://github.com/TrueConf/python-trueconf-room/issues
Keywords: trueconf,room,api,framework,wrapper,websocket
Classifier: Development Status :: 5 - Production/Stable
Classifier: Environment :: Console
Classifier: Intended Audience :: Developers
Classifier: Programming Language :: Python :: 3.9
Classifier: Programming Language :: Python :: 3.10
Classifier: Programming Language :: Python :: 3.11
Classifier: Programming Language :: Python :: 3.12
Classifier: Programming Language :: Python :: 3.13
Classifier: Topic :: Software Development :: Libraries :: Python Modules
Requires-Python: >=3.9
License-File: LICENSE
Requires-Dist: websocket-client==0.58
Requires-Dist: requests
Dynamic: license-file
